MANIFEST.in
README.md
setup.py
furi/__init__.py
furi/aws.py
furi/exceptions.py
furi/furifile.py
furi/furimap.py
furi/sftp.py
furi/utils.py
furi.egg-info/PKG-INFO
furi.egg-info/SOURCES.txt
furi.egg-info/dependency_links.txt
furi.egg-info/requires.txt
furi.egg-info/top_level.txt
test/test_furifile.py