Metadata-Version: 1.1
Name: furi
Version: 0.6.12
Summary: fURI File access through URIs.
Home-page: http://www.smallweirdnumber.com
Author: amancevice
Author-email: smallweirdnum@gmail.com
License: UNKNOWN
Platform: UNKNOWN
Classifier: Development Status :: 3 - Alpha
Classifier: Intended Audience :: Developers
Classifier: Intended Audience :: System Administrators
Classifier: License :: OSI Approved :: MIT License
Classifier: Operating System :: OS Independent
Classifier: Programming Language :: Python :: 2.7
Classifier: Topic :: Utilities
